Metadata-Version: 2.1
Name: mess-server-first
Version: 0.1
Summary: mess_server
Home-page: UNKNOWN
Author: Tatiana Kudryavtseva
Author-email: lexta@list.ru
License: UNKNOWN
Platform: UNKNOWN
